MANIFEST.in
README
setup.cfg
setup.py
gui_ssh_client/__init__.py
gui_ssh_client/main.py
gui_ssh_client.egg-info/PKG-INFO
gui_ssh_client.egg-info/SOURCES.txt
gui_ssh_client.egg-info/dependency_links.txt
gui_ssh_client.egg-info/entry_points.txt
gui_ssh_client.egg-info/requires.txt
gui_ssh_client.egg-info/top_level.txt
gui_ssh_client/data/enve.png
gui_ssh_client/data/pc-3.png
gui_ssh_client/src/__init__.py
gui_ssh_client/src/canvas.py
gui_ssh_client/src/credentials.txt
gui_ssh_client/src/shell.py